NiukeKuaixiaoXingyeQiuzhiGonglveDanengPian20212022/README.md
NiukeKuaixiaoXingyeQiuzhiGonglveDanengPian20212022/__init__.py
NiukeKuaixiaoXingyeQiuzhiGonglveDanengPian20212022/__main__.py
NiukeKuaixiaoXingyeQiuzhiGonglveDanengPian20212022/file.epub
NiukeKuaixiaoXingyeQiuzhiGonglveDanengPian20212022/index.html
NiukeKuaixiaoXingyeQiuzhiGonglveDanengPian20212022/css/__init__.py
NiukeKuaixiaoXingyeQiuzhiGonglveDanengPian20212022/css/annotations.css
NiukeKuaixiaoXingyeQiuzhiGonglveDanengPian20212022/css/main.css
NiukeKuaixiaoXingyeQiuzhiGonglveDanengPian20212022/css/normalize.css
NiukeKuaixiaoXingyeQiuzhiGonglveDanengPian20212022/css/popup.css
NiukeKuaixiaoXingyeQiuzhiGonglveDanengPian20212022/font/__init__.py
NiukeKuaixiaoXingyeQiuzhiGonglveDanengPian20212022/font/fontello.eot
NiukeKuaixiaoXingyeQiuzhiGonglveDanengPian20212022/font/fontello.svg
NiukeKuaixiaoXingyeQiuzhiGonglveDanengPian20212022/font/fontello.ttf
NiukeKuaixiaoXingyeQiuzhiGonglveDanengPian20212022/font/fontello.woff
NiukeKuaixiaoXingyeQiuzhiGonglveDanengPian20212022/img/__init__.py
NiukeKuaixiaoXingyeQiuzhiGonglveDanengPian20212022/img/annotator-glyph-sprite.png
NiukeKuaixiaoXingyeQiuzhiGonglveDanengPian20212022/img/annotator-icon-sprite.png
NiukeKuaixiaoXingyeQiuzhiGonglveDanengPian20212022/img/apple-touch-icon.png
NiukeKuaixiaoXingyeQiuzhiGonglveDanengPian20212022/img/cancelfullscreen.png
NiukeKuaixiaoXingyeQiuzhiGonglveDanengPian20212022/img/close.png
NiukeKuaixiaoXingyeQiuzhiGonglveDanengPian20212022/img/fullscreen.png
NiukeKuaixiaoXingyeQiuzhiGonglveDanengPian20212022/img/loader.gif
NiukeKuaixiaoXingyeQiuzhiGonglveDanengPian20212022/img/menu-icon.png
NiukeKuaixiaoXingyeQiuzhiGonglveDanengPian20212022/img/save.png
NiukeKuaixiaoXingyeQiuzhiGonglveDanengPian20212022/img/saved.png
NiukeKuaixiaoXingyeQiuzhiGonglveDanengPian20212022/img/settings-s.png
NiukeKuaixiaoXingyeQiuzhiGonglveDanengPian20212022/img/settings.png
NiukeKuaixiaoXingyeQiuzhiGonglveDanengPian20212022/img/star.png
niuke_kuaixiao_xingye_qiuzhi_gonglve_daneng_pian_2021_2022-2024.3.6.0.dist-info/METADATA
niuke_kuaixiao_xingye_qiuzhi_gonglve_daneng_pian_2021_2022-2024.3.6.0.dist-info/WHEEL
niuke_kuaixiao_xingye_qiuzhi_gonglve_daneng_pian_2021_2022-2024.3.6.0.dist-info/entry_points.txt
niuke_kuaixiao_xingye_qiuzhi_gonglve_daneng_pian_2021_2022-2024.3.6.0.dist-info/top_level.txt
niuke_kuaixiao_xingye_qiuzhi_gonglve_daneng_pian_2021_2022-2024.3.6.0.dist-info/RECORD
